flake8_multiline_function_call_equals.py
test/__init__.py
test/collector.py
test/insert_project.py
test/lib.py
test/masterCollector.py
test/sel_lib.py
test/tests.py
flake8_multiline_function_call_equals-0.1.4.dist-info/LICENSE
flake8_multiline_function_call_equals-0.1.4.dist-info/METADATA
flake8_multiline_function_call_equals-0.1.4.dist-info/WHEEL
flake8_multiline_function_call_equals-0.1.4.dist-info/entry_points.txt
flake8_multiline_function_call_equals-0.1.4.dist-info/top_level.txt
flake8_multiline_function_call_equals-0.1.4.dist-info/RECORD
